pymotion/__init__.py
pymotion/io/__init__.py
pymotion/io/bvh.py
pymotion/ops/__init__.py
pymotion/ops/center_of_mass.py
pymotion/ops/center_of_mass_torch.py
pymotion/ops/skeleton.py
pymotion/ops/skeleton_torch.py
pymotion/ops/time.py
pymotion/ops/time_torch.py
pymotion/ops/vector.py
pymotion/ops/vector_torch.py
pymotion/render/__init__.py
pymotion/render/blender.py
pymotion/render/viewer.py
pymotion/render/internal/pymotion_blender.py
pymotion/rotations/__init__.py
pymotion/rotations/dual_quat.py
pymotion/rotations/dual_quat_torch.py
pymotion/rotations/ortho6d.py
pymotion/rotations/ortho6d_torch.py
pymotion/rotations/quat.py
pymotion/rotations/quat_torch.py
upc_pymotion-0.2.3.dist-info/METADATA
upc_pymotion-0.2.3.dist-info/WHEEL
upc_pymotion-0.2.3.dist-info/licenses/LICENSE
upc_pymotion-0.2.3.dist-info/RECORD
