Metadata-Version: 2.4
Name: upc-pymotion
Version: 0.2.3
Summary: A Python library for working with motion data in NumPy or PyTorch.
Project-URL: Homepage, https://github.com/UPC-ViRVIG/pymotion
Author-email: Jose Luis Ponton <jose.luis.ponton@upc.edu>
License: MIT License
License-File: LICENSE
Keywords: blender,dual quaternion,forward kinematics,motion,numpy,pytorch,quaternion,rotation matrix,skeleton
Classifier: Programming Language :: Python
Classifier: Programming Language :: Python :: 3
Requires-Python: >=3.0
Requires-Dist: numpy>=1.20.0
Provides-Extra: pytorch
Requires-Dist: torch; extra == 'pytorch'
Requires-Dist: torchaudio; extra == 'pytorch'
Requires-Dist: torchvision; extra == 'pytorch'
Provides-Extra: test
Requires-Dist: pytest; extra == 'test'
Provides-Extra: viewer
Requires-Dist: dash; extra == 'viewer'
Requires-Dist: dash-bootstrap-components; extra == 'viewer'
Requires-Dist: plotly; extra == 'viewer'
